harnessutils/__init__.py
harnessutils/config.py
harnessutils/manager.py
harnessutils/py.typed
harnessutils/types.py
harnessutils/compaction/__init__.py
harnessutils/compaction/pruning.py
harnessutils/compaction/summarization.py
harnessutils/compaction/truncation.py
harnessutils/conversion/__init__.py
harnessutils/conversion/to_model.py
harnessutils/models/__init__.py
harnessutils/models/conversation.py
harnessutils/models/message.py
harnessutils/models/parts.py
harnessutils/models/usage.py
harnessutils/storage/__init__.py
harnessutils/storage/filesystem.py
harnessutils/storage/memory.py
harnessutils/tokens/__init__.py
harnessutils/tokens/estimator.py
harnessutils/turn/__init__.py
harnessutils/turn/hooks.py
harnessutils/turn/processor.py
harnessutils/turn/state_machine.py
harnessutils/utils/__init__.py
harnessutils/utils/ids.py
harness_utils-0.1.1.dist-info/METADATA
harness_utils-0.1.1.dist-info/WHEEL
harness_utils-0.1.1.dist-info/licenses/LICENSE
harness_utils-0.1.1.dist-info/RECORD
