Metadata-Version: 2.4
Name: harness-utils
Version: 0.1.1
Summary: Context window management utilities for LLM-based applications
Author-email: Jeremy Tregunna <jeremy@tregunna.ca>
License: MIT
License-File: LICENSE
Keywords: ai,chatbot,context-management,context-window,conversation,llm,prompt-engineering,token-management
Classifier: Development Status :: 4 - Beta
Classifier: Intended Audience :: Developers
Classifier: License :: OSI Approved :: MIT License
Classifier: Programming Language :: Python :: 3
Classifier: Programming Language :: Python :: 3.12
Classifier: Programming Language :: Python :: 3.13
Classifier: Programming Language :: Python :: 3.14
Classifier: Topic :: Scientific/Engineering :: Artificial Intelligence
Classifier: Topic :: Software Development :: Libraries :: Python Modules
Classifier: Typing :: Typed
Requires-Python: >=3.12
